ao2pyv.py
ao2pyv-0.1.1.dist-info/RECORD
ao2pyv-0.1.1.dist-info/METADATA
ao2pyv-0.1.1.dist-info/DESCRIPTION.rst
ao2pyv-0.1.1.dist-info/top_level.txt
ao2pyv-0.1.1.dist-info/metadata.json
ao2pyv-0.1.1.dist-info/WHEEL
ao2pyv-0.1.1.dist-info/entry_points.txt
