Metadata-Version: 2.0
Name: ao2pyv
Version: 0.1.1
Summary: Converts Archive.org video searches into PyVideo.org API submissions.
Home-page: https://github.com/hodgestar/ao2pyv
Author: Simon Cross
Author-email: hodgestar@gmail.com
License: BSD
Platform: UNKNOWN
Classifier: Development Status :: 4 - Beta
Classifier: Intended Audience :: Developers
Classifier: License :: OSI Approved :: BSD License
Classifier: Operating System :: POSIX
Classifier: Programming Language :: Python
Classifier: Topic :: Software Development :: Libraries :: Python Modules
Classifier: Topic :: Internet :: WWW/HTTP
Requires-Dist: requests
Requires-Dist: click
